{
    "373115910971719681": {
      "country": "España",
      "countryCode": "es"
    },
    "156498688611581959": {
      "country": "Venezuela",
      "countryCode": "ve"
    },
    "497201773811990538": {
      "country": "Perú",
      "countryCode": "pe"
    },
    "694624255358402560": {
      "country": "Bolivia",
      "countryCode": "bo"
    },
    "1003465475411419257": {
      "country": "Chile",
      "countryCode": "cl"
    },
    "740358234002686004": {
      "country": "Perú",
      "countryCode": "pe"
    },
    "1097672583694004310": {
      "country": "Perú",
      "countryCode": "pe"
    },
    "401845716991082496": {
      "country": "Argentina",
      "countryCode": "ar"
    },
    "1023321295259181179": {
      "country": "España",
      "countryCode": "es"
    },
    "852588734104469535": {
      "country": "México",
      "countryCode": "mx"
    },
    "395448252528459777": {
      "country": "México",
      "countryCode": "mx"
    },
    "254720311717658624": {
      "country": "México",
      "countryCode": "mx"
    },
    "602240617862660096": {
      "country": "Argentina",
      "countryCode": "ar"
    },
    "415680145660182529": {
      "country": "Colombia",
      "countryCode": "co"
    }
  }